BancoRegs/reg16bit.vhd
library ieee;
use ieee.std_logic_1164.all;
use ieee.numeric_std.all;

-- João Pedro de Andrade Argenton e Lucas Maciel Ferreira

entity reg16bit is
    port (
        clk     : in std_logic;
        rst     : in std_logic;
        wr_en   : in std_logic;
        data_in : in unsigned(15 downto 0);
        data_out: out unsigned(15 downto 0)
    );
end entity;

architecture behavioral of reg16bit is
    signal registro: unsigned(15 downto 0);
begin
    process(clk, rst, wr_en)
    begin
        if rst='1' then
            registro <= "0000000000000000";
        elsif wr_en='1' then
            if rising_edge(clk) then
                registro <= data_in;
            end if;
        end if;
    end process;
    data_out <= registro;
end architecture;

BancoRegs/banco_regs.vhd
library ieee;
use ieee.std_logic_1164.all;
use ieee.numeric_std.all;

-- João Pedro de Andrade Argenton e Lucas Maciel Ferreira

entity Banco_regs is
    port (
        clk         : in std_logic;
        rst         : in std_logic;
        wr_en       : in std_logic;
        w_address   : in std_logic_vector(3 downto 0);
        r_address   : in std_logic_vector(3 downto 0);
        data_in     : in unsigned(15 downto 0);
        data_out    : out unsigned(15 downto 0)
    );
end entity;

architecture structural of Banco_regs is
    signal we0, we1, we2, we3, we4, we5, we6, we7, we8, we9 : std_logic;
    signal registrador_0: unsigned(15 downto 0);
    signal registrador_1: unsigned(15 downto 0);
    signal registrador_2: unsigned(15 downto 0);
    signal registrador_3: unsigned(15 downto 0);
    signal registrador_4: unsigned(15 downto 0);
    signal registrador_5: unsigned(15 downto 0);
    signal registrador_6: unsigned(15 downto 0);
    signal registrador_7: unsigned(15 downto 0);
    signal registrador_8: unsigned(15 downto 0);
    signal registrador_9: unsigned(15 downto 0);

begin
    process(clk, rst, wr_en)
    begin

        reg0 : entity work.reg16bit
        port map(
            clk => clk,
            rst => rst,
            wr_en => we0,
            data_in => data_in,
            data_out => registrador_0
        );

        reg1 : entity work.reg16bit
        port map(
            clk => clk,
            rst => rst,
            wr_en => we1,
            data_in => data_in,
            data_out => registrador_1
        );

        reg2 : entity work.reg16bit
        port map(
            clk => clk,
            rst => rst,
            wr_en => we2,
            data_in => data_in,
            data_out => registrador_2
        );

        reg3 : entity work.reg16bit
        port map(
            clk => clk,
            rst => rst,
            wr_en => we3,
            data_in => data_in,
            data_out => registrador_3
        );

        reg4 : entity work.reg16bit
        port map(
            clk => clk,
            rst => rst,
            wr_en => we4,
            data_in => data_in,
            data_out => registrador_4
        );

        reg5 : entity work.reg16bit
        port map(
            clk => clk,
            rst => rst,
            wr_en => we5,
            data_in => data_in,
            data_out => registrador_5
        );

        reg6 : entity work.reg16bit
        port map(
            clk => clk,
            rst => rst,
            wr_en => we6,
            data_in => data_in,
            data_out => registrador_6
        );

        reg7 : entity work.reg16bit
        port map(
            clk => clk,
            rst => rst,
            wr_en => we7,
            data_in => data_in,
            data_out => registrador_7
        );

        reg8 : entity work.reg16bit
        port map(
            clk => clk,
            rst => rst,
            wr_en => we8,
            data_in => data_in,
            data_out => registrador_8
        );

        reg9 : entity work.reg16bit
        port map(
            clk => clk,
            rst => rst,
            wr_en => we9,
            data_in => data_in,
            data_out => registrador_9
        );

        we0 <= '1' when w_address = "0000" else '0';
        we1 <= '1' when w_address = "0001" else '0';
        we2 <= '1' when w_address = "0010" else '0';
        we3 <= '1' when w_address = "0011" else '0';
        we4 <= '1' when w_address = "0100" else '0';
        we5 <= '1' when w_address = "0101" else '0';
        we6 <= '1' when w_address = "0110" else '0';
        we7 <= '1' when w_address = "0111" else '0';
        we8 <= '1' when w_address = "1000" else '0';
        we9 <= '1' when w_address = "1001" else '0';

        data_out <= registrador_0 when r_address = "0000" else
                    registrador_1 when r_address = "0001" else
                    registrador_2 when r_address = "0010" else
                    registrador_3 when r_address = "0011" else
                    registrador_4 when r_address = "0100" else
                    registrador_5 when r_address = "0101" else
                    registrador_6 when r_address = "0110" else
                    registrador_7 when r_address = "0111" else
                    registrador_8 when r_address = "1000" else
                    registrador_9 when r_address = "1001" else
                    "0000000000000000";
                    
end architecture;

BancoRegs/banco_regs_tb.vhd
library ieee;
use ieee.std_logic_1164.all;
use ieee.numeric_std.all;

-- João Pedro de Andrade Argenton e Lucas Maciel Ferreira

entity banco_regs_tb is
end entity;

architecture testbench of banco_regs_tb is
signal period_time          : time      := 100 ns;
signal finished             : std_logic := '0';
signal clk, rst, wr_en      : std_logic;
signal w_address, r_address : std_logic_vector(3 downto 0);    
signal data_in, data_out    : unsigned(15 downto 0);

begin
    uut : entity work.banco_regs
    port map(
        clk         => clk,
        rst         => rst,
        wr_en       => wr_en,      
        w_address   => w_address,
        r_address   => r_address,
        data_in     => data_in,
        data_out    => data_out
    );

    reset_global: process
    begin
        rst <= '1';
        wait for period_time*2;
        rst <= '0';
        wait;
    end process reset_global;

    sim_time_proc: process
    begin
        wait for 10 us;
        finished <= '1';
        wait;
    end process sim_time_proc;

    clk_proc: process
    begin
        while finished /= '1' loop
            clk <= '0';
            wait for period_time/2;
            clk <= '1';
            wait for period_time/2;
        end loop;
        wait;
    end process clk_proc;

    process
    begin
        wait for period_time;
        w_address <= "0001";
        r_address <= "0000";
        wr_en <= '0';
        data_in <= "0000000000001010";
        wait for period_time;
        w_address <= "0001";
        r_address <= "0001";
        wr_en <= '0';
        data_in <= "0000000000001010";
        wait for period_time;
        w_address <= "1001";
        r_address <= "0001";
        wr_en <= '1';
        data_in <= "0000000000000010";
        wait for period_time;
        w_address <= "0001";
        r_address <= "0000";
        wr_en <= '0';
        data_in <= "1111111111111111";
        wait;
    end process;
end architecture;

BancoRegs/banco_regs_tb.vcd
$date
  Wed May 21 16:24:06 2025
$end
$version
  GHDL v0
$end
$timescale
  1 fs
$end
$scope module standard $end
$upscope $end
$scope module std_logic_1164 $end
$upscope $end
$scope module numeric_std $end
$upscope $end
$scope module banco_regs_tb $end
$comment period_time is not handled $end
$var reg 1 ! finished $end
$var reg 1 " clk $end
$var reg 1 # rst $end
$var reg 1 $ wr_en $end
$var reg 4 % w_address[3:0] $end
$var reg 4 & r_address[3:0] $end
$var reg 16 ' data_in[15:0] $end
$var reg 16 ( data_out[15:0] $end
$scope module uut $end
$var reg 1 ) clk $end
$var reg 1 * rst $end
$var reg 1 + wr_en $end
$var reg 4 , w_address[3:0] $end
$var reg 4 - r_address[3:0] $end
$var reg 16 . data_in[15:0] $end
$var reg 16 / data_out[15:0] $end
$var reg 1 0 we0 $end
$var reg 1 1 we1 $end
$var reg 1 2 we2 $end
$var reg 1 3 we3 $end
$var reg 1 4 we4 $end
$var reg 1 5 we5 $end
$var reg 1 6 we6 $end
$var reg 1 7 we7 $end
$var reg 1 8 we8 $end
$var reg 1 9 we9 $end
$var reg 16 : registrador_0[15:0] $end
$var reg 16 ; registrador_1[15:0] $end
$var reg 16 < registrador_2[15:0] $end
$var reg 16 = registrador_3[15:0] $end
$var reg 16 > registrador_4[15:0] $end
$var reg 16 ? registrador_5[15:0] $end
$var reg 16 @ registrador_6[15:0] $end
$var reg 16 A registrador_7[15:0] $end
$var reg 16 B registrador_8[15:0] $end
$var reg 16 C registrador_9[15:0] $end
$scope module reg0 $end
$var reg 1 D clk $end
$var reg 1 E rst $end
$var reg 1 F wr_en $end
$var reg 16 G data_in[15:0] $end
$var reg 16 H data_out[15:0] $end
$var reg 16 I registro[15:0] $end
$upscope $end
$scope module reg1 $end
$var reg 1 J clk $end
$var reg 1 K rst $end
$var reg 1 L wr_en $end
$var reg 16 M data_in[15:0] $end
$var reg 16 N data_out[15:0] $end
$var reg 16 O registro[15:0] $end
$upscope $end
$scope module reg2 $end
$var reg 1 P clk $end
$var reg 1 Q rst $end
$var reg 1 R wr_en $end
$var reg 16 S data_in[15:0] $end
$var reg 16 T data_out[15:0] $end
$var reg 16 U registro[15:0] $end
$upscope $end
$scope module reg3 $end
$var reg 1 V clk $end
$var reg 1 W rst $end
$var reg 1 X wr_en $end
$var reg 16 Y data_in[15:0] $end
$var reg 16 Z data_out[15:0] $end
$var reg 16 [ registro[15:0] $end
$upscope $end
$scope module reg4 $end
$var reg 1 \ clk $end
$var reg 1 ] rst $end
$var reg 1 ^ wr_en $end
$var reg 16 _ data_in[15:0] $end
$var reg 16 ` data_out[15:0] $end
$var reg 16 a registro[15:0] $end
$upscope $end
$scope module reg5 $end
$var reg 1 b clk $end
$var reg 1 c rst $end
$var reg 1 d wr_en $end
$var reg 16 e data_in[15:0] $end
$var reg 16 f data_out[15:0] $end
$var reg 16 g registro[15:0] $end
$upscope $end
$scope module reg6 $end
$var reg 1 h clk $end
$var reg 1 i rst $end
$var reg 1 j wr_en $end
$var reg 16 k data_in[15:0] $end
$var reg 16 l data_out[15:0] $end
$var reg 16 m registro[15:0] $end
$upscope $end
$scope module reg7 $end
$var reg 1 n clk $end
$var reg 1 o rst $end
$var reg 1 p wr_en $end
$var reg 16 q data_in[15:0] $end
$var reg 16 r data_out[15:0] $end
$var reg 16 s registro[15:0] $end
$upscope $end
$scope module reg8 $end
$var reg 1 t clk $end
$var reg 1 u rst $end
$var reg 1 v wr_en $end
$var reg 16 w data_in[15:0] $end
$var reg 16 x data_out[15:0] $end
$var reg 16 y registro[15:0] $end
$upscope $end
$scope module reg9 $end
$var reg 1 z clk $end
$var reg 1 { rst $end
$var reg 1 | wr_en $end
$var reg 16 } data_in[15:0] $end
$var reg 16 !" data_out[15:0] $end
$var reg 16 "" registro[15:0] $end
$upscope $end
$upscope $end
$upscope $end
$enddefinitions $end
#0
0!
0"
1#
U$
bUUUU %
bUUUU &
bUUUUUUUUUUUUUUUU '
b0000000000000000 (
0)
1*
U+
bUUUU ,
bUUUU -
bUUUUUUUUUUUUUUUU .
b0000000000000000 /
00
01
02
03
04
05
06
07
08
09
b0000000000000000 :
b0000000000000000 ;
b0000000000000000 <
b0000000000000000 =
b0000000000000000 >
b0000000000000000 ?
b0000000000000000 @
b0000000000000000 A
b0000000000000000 B
b0000000000000000 C
0D
1E
0F
bUUUUUUUUUUUUUUUU G
b0000000000000000 H
b0000000000000000 I
0J
1K
0L
bUUUUUUUUUUUUUUUU M
b0000000000000000 N
b0000000000000000 O
0P
1Q
0R
bUUUUUUUUUUUUUUUU S
b0000000000000000 T
b0000000000000000 U
0V
1W
0X
bUUUUUUUUUUUUUUUU Y
b0000000000000000 Z
b0000000000000000 [
0\
1]
0^
bUUUUUUUUUUUUUUUU _
b0000000000000000 `
b0000000000000000 a
0b
1c
0d
bUUUUUUUUUUUUUUUU e
b0000000000000000 f
b0000000000000000 g
0h
1i
0j
bUUUUUUUUUUUUUUUU k
b0000000000000000 l
b0000000000000000 m
0n
1o
0p
bUUUUUUUUUUUUUUUU q
b0000000000000000 r
b0000000000000000 s
0t
1u
0v
bUUUUUUUUUUUUUUUU w
b0000000000000000 x
b0000000000000000 y
0z
1{
0|
bUUUUUUUUUUUUUUUU }
b0000000000000000 !"
b0000000000000000 ""
#50000000
1"
1)
1D
1J
1P
1V
1\
1b
1h
1n
1t
1z
#100000000
0"
0$
b0001 %
b0000 &
b0000000000001010 '
0)
0+
b0001 ,
b0000 -
b0000000000001010 .
11
0D
b0000000000001010 G
0J
1L
b0000000000001010 M
0P
b0000000000001010 S
0V
b0000000000001010 Y
0\
b0000000000001010 _
0b
b0000000000001010 e
0h
b0000000000001010 k
0n
b0000000000001010 q
0t
b0000000000001010 w
0z
b0000000000001010 }
#150000000
1"
1)
1D
1J
1P
1V
1\
1b
1h
1n
1t
1z
#200000000
0"
0#
1$
b0001 &
0)
0*
1+
b0001 -
0D
0E
0J
0K
0P
0Q
0V
0W
0\
0]
0b
0c
0h
0i
0n
0o
0t
0u
0z
0{
#250000000
1"
b0000000000001010 (
1)
b0000000000001010 /
b0000000000001010 ;
1D
1J
b0000000000001010 N
b0000000000001010 O
1P
1V
1\
1b
1h
1n
1t
1z
#300000000
0"
b1001 %
b0000000000000010 '
0)
b1001 ,
b0000000000000010 .
01
19
0D
b0000000000000010 G
0J
0L
b0000000000000010 M
0P
b0000000000000010 S
0V
b0000000000000010 Y
0\
b0000000000000010 _
0b
b0000000000000010 e
0h
b0000000000000010 k
0n
b0000000000000010 q
0t
b0000000000000010 w
0z
1|
b0000000000000010 }
#350000000
1"
1)
b0000000000000010 C
1D
1J
1P
1V
1\
1b
1h
1n
1t
1z
b0000000000000010 !"
b0000000000000010 ""
#400000000
0"
0$
b0001 %
b1010 &
b1111111111111111 '
b0000000000000000 (
0)
0+
b0001 ,
b1010 -
b1111111111111111 .
b0000000000000000 /
11
09
0D
b1111111111111111 G
0J
1L
b1111111111111111 M
0P
b1111111111111111 S
0V
b1111111111111111 Y
0\
b1111111111111111 _
0b
b1111111111111111 e
0h
b1111111111111111 k
0n
b1111111111111111 q
0t
b1111111111111111 w
0z
0|
b1111111111111111 }
#450000000
1"
1)
b1111111111111111 ;
1D
1J
b1111111111111111 N
b1111111111111111 O
1P
1V
1\
1b
1h
1n
1t
1z
