ULA/ULA.vhd
library ieee;
use ieee.std_logic.all;
use ieee.numeric_std.all;

-- João Pedro de Andrade Argenton e Lucas Maciel Ferreira
-- Operações escolhidas: adição, subtração, decremento, 'ou' lógico, 'e' lógico e 'ou' exclusivo

entity ULA is 
port (
    input_A : in unsigned(15 downto 0);
    input_B : in unsigned(15 downto 0);
    result  : out unsigned(15 downto 0);

    operation   : in std_logic_vector(2 downto 0);

    zero    : out std_logic;
    negative: out std_logic;
    carry   : out std_logic;
    overflow: out std_logic
    );
end entity;

architecture behavioral of ULA is
    signal calc: unsigned(15 downto 0);

begin
    calc <= (input_A + input_B) when operation = "000" else                 -- Adicao
                (input_B - "0000000000000001") when operation = "001" else  -- Decremento
                (input_A - input_B) when operation = "010" else             -- Subtracao
                (input_A or input_B) when operation = "100" else            -- Ou lógico
                (input_A and input_B) when operation = "101" else           -- E lógico
                (input_A xor input_B) when operation = "110" else           -- Ou exclusivo
                "0000000000000000";

    result <= calc;
    zero <= '1' when (calc = "0000000000000000") else '0';
    negative <= calc(15);
    carry <= '1' when calc < input_A else '0';
    overflow <= '1' when (input_A(15) and input_B(15) and not calc(15)) 
                or (not input_A(15) and not input_B(15) and calc(15)) else 
                '0';
    
end behavioral;

BancoRegs/reg16bit.vhd
library ieee;
use ieee.std_logic_1164.all;
use ieee.numeric_std.all;

-- João Pedro de Andrade Argenton e Lucas Maciel Ferreira

entity reg16bit is
    port (
        clk     : in std_logic;
        rst     : in std_logic;
        wr_en   : in std_logic;
        data_in : in unsigned(15 downto 0);
        data_out: out unsigned(15 downto 0)
    );
end entity;

architecture behavioral of reg16bit is
    signal registro: unsigned(15 downto 0);
begin
    process(clk, rst, wr_en)
    begin
        if rst='1' then
            registro <= "0000000000000000";
        elsif wr_en='1' then
            if rising_edge(clk) then
                registro <= data_in;
            end if;
        end if;
    end process;
    data_out <= registro;
end architecture;

BancoRegs/banco_regs.vhd
library ieee;
use ieee.std_logic_1164.all;
use ieee.numeric_std.all;

-- João Pedro de Andrade Argenton e Lucas Maciel Ferreira

entity Banco_regs is
    port (
        clk         : in std_logic;
        rst         : in std_logic;
        wr_en       : in std_logic;
        w_address   : in std_logic_vector(3 downto 0);
        r_address   : in std_logic_vector(3 downto 0);
        data_in     : in unsigned(15 downto 0);
        data_out    : out unsigned(15 downto 0)
    );
end entity;

architecture structural of Banco_regs is
    signal we0, we1, we2, we3, we4, we5, we6, we7, we8, we9 : std_logic;
    signal registrador_0: unsigned(15 downto 0);
    signal registrador_1: unsigned(15 downto 0);
    signal registrador_2: unsigned(15 downto 0);
    signal registrador_3: unsigned(15 downto 0);
    signal registrador_4: unsigned(15 downto 0);
    signal registrador_5: unsigned(15 downto 0);
    signal registrador_6: unsigned(15 downto 0);
    signal registrador_7: unsigned(15 downto 0);
    signal registrador_8: unsigned(15 downto 0);
    signal registrador_9: unsigned(15 downto 0);

begin
    process(clk, rst, wr_en)
    begin

        reg0 : entity work.reg16bit
        port map(
            clk => clk,
            rst => rst,
            wr_en => we0,
            data_in => data_in,
            data_out => registrador_0
        );

        reg1 : entity work.reg16bit
        port map(
            clk => clk,
            rst => rst,
            wr_en => we1,
            data_in => data_in,
            data_out => registrador_1
        );

        reg2 : entity work.reg16bit
        port map(
            clk => clk,
            rst => rst,
            wr_en => we2,
            data_in => data_in,
            data_out => registrador_2
        );

        reg3 : entity work.reg16bit
        port map(
            clk => clk,
            rst => rst,
            wr_en => we3,
            data_in => data_in,
            data_out => registrador_3
        );

        reg4 : entity work.reg16bit
        port map(
            clk => clk,
            rst => rst,
            wr_en => we4,
            data_in => data_in,
            data_out => registrador_4
        );

        reg5 : entity work.reg16bit
        port map(
            clk => clk,
            rst => rst,
            wr_en => we5,
            data_in => data_in,
            data_out => registrador_5
        );

        reg6 : entity work.reg16bit
        port map(
            clk => clk,
            rst => rst,
            wr_en => we6,
            data_in => data_in,
            data_out => registrador_6
        );

        reg7 : entity work.reg16bit
        port map(
            clk => clk,
            rst => rst,
            wr_en => we7,
            data_in => data_in,
            data_out => registrador_7
        );

        reg8 : entity work.reg16bit
        port map(
            clk => clk,
            rst => rst,
            wr_en => we8,
            data_in => data_in,
            data_out => registrador_8
        );

        reg9 : entity work.reg16bit
        port map(
            clk => clk,
            rst => rst,
            wr_en => we9,
            data_in => data_in,
            data_out => registrador_9
        );

        we0 <= '1' when w_address = "0000" else '0';
        we1 <= '1' when w_address = "0001" else '0';
        we2 <= '1' when w_address = "0010" else '0';
        we3 <= '1' when w_address = "0011" else '0';
        we4 <= '1' when w_address = "0100" else '0';
        we5 <= '1' when w_address = "0101" else '0';
        we6 <= '1' when w_address = "0110" else '0';
        we7 <= '1' when w_address = "0111" else '0';
        we8 <= '1' when w_address = "1000" else '0';
        we9 <= '1' when w_address = "1001" else '0';

        data_out <= registrador_0 when r_address = "0000" else
                    registrador_1 when r_address = "0001" else
                    registrador_2 when r_address = "0010" else
                    registrador_3 when r_address = "0011" else
                    registrador_4 when r_address = "0100" else
                    registrador_5 when r_address = "0101" else
                    registrador_6 when r_address = "0110" else
                    registrador_7 when r_address = "0111" else
                    registrador_8 when r_address = "1000" else
                    registrador_9 when r_address = "1001" else
                    "0000000000000000";
                    
end architecture;

Top_Level.vhd
library ieee;
use ieee.std_logic_1164.all;
use ieee.numeric_std.all;

-- João Pedro de Andrade Argenton e Lucas Maciel Ferreira

entity Top_Level is
    port(
        A_source    : in std_logic_vector(1 downto 0);
        B_source    : in std_logic;
        REG_source  : in std_logic;
        clk         : in std_logic;
        rst         : in std_logic;
        A_rst       : in std_logic;
        wr_en       : in std_logic;
        A_wr_en     : in std_logic;
        operation   : in std_logic_vector(2 downto 0);
        w_address   : in std_logic_vector(3 downto 0);
        r_address   : in std_logic_vector(3 downto 0);
        immediate   : in unsigned(15 downto 0);
        zero        : out std_logic;
        negative    : out std_logic;
        carry       : out std_logic;
        overflow    : out std_logic;
        reg, regA   : out unsigned(15 downto 0) -- Apenas para TESTE
    );
end entity;

architecture structural of Top_Level is
    signal acum_out, acum_in, banco_out, ULA_out: unsigned(15 downto 0);
    signal operando_B, reg_in                   : unsigned(15 downto 0);
begin
    acumulador : entity work.reg16bit
    port map(
        clk => clk,
        rst => A_rst,
        wr_en => A_wr_en,
        data_in => acum_in,
        data_out => acum_out
    );

    banco : entity work.Banco_regs
    port map(
        clk => clk,
        rst => rst,
        wr_en => wr_en,
        w_address => w_address,
        r_address => r_address,
        data_in => reg_in,
        data_out => banco_out
    );

    ULA : entity work.ULA
    port map(
        input_A => acum_out,
        input_B => operando_B,
        result => ULA_out,
        operation => operation,
        zero => zero,
        negative => negative,
        carry => carry,
        overflow => overflow
    );

    acum_in     <= ULA_out when A_source = "00" else immediate when A_source = "01" else banco_out;
    operando_B  <= banco_out when B_source = '0' else immediate;
    reg_in      <= acum_out when REG_source = '0' else immediate;
    reg         <= banco_out;
    regA        <= acum_out;

end architecture;

Top_Level_tb.vhd
library ieee;
use ieee.std_logic_1164.all;
use ieee.numeric_std.all;

entity Top_Level_tb is
end entity;

architecture testbech of Top_Level_tb is
    signal period_time                      : time      := 100 ns;
    signal finished                         : std_logic := '0';
    signal clk, rst, wr_en                  : std_logic;
    signal B_source, A_rst, A_wr_en         : std_logic;                
    signal A_source                         : std_logic_vector(1 downto 0);
    signal operation                        : std_logic_vector(2 downto 0);
    signal reg_source                       : std_logic;
    signal w_address, r_address             : std_logic_vector(3 downto 0);
    signal immediate                        : unsigned(15 downto 0);
    signal zero, negative, carry, overflow  : std_logic;
    signal reg, regA                        : unsigned(15 downto 0);
    -- os vetores e unsigned nao apareciam no gtkwave, encontramos essa solução online
    -- o problema nao foi resolvido após adicionar essa passagem, porém ficamos com medo de tirar e qubrar 
    -- a simulação no futuro 
    attribute keep : boolean;
    attribute keep of A_source   : signal is true;
    attribute keep of operation  : signal is true;
    attribute keep of w_address  : signal is true;
    attribute keep of r_address  : signal is true;
    attribute keep of immediate  : signal is true;
    attribute keep of reg        : signal is true;
    attribute keep of regA       : signal is true;

begin
    uut : entity work.Top_Level
    port map(
        A_source    => A_source,
        B_source    => B_source,
        Reg_source  => reg_source,
        clk         => clk,
        rst         => rst,
        A_rst       => A_rst,
        wr_en       => wr_en,
        A_wr_en     => A_wr_en,
        operation   => operation,
        w_address   => w_address,
        r_address   => r_address,
        immediate   => immediate,
        zero        => zero,
        negative    => negative,
        carry       => carry,
        overflow    => overflow,
        reg         => reg,
        regA        => regA
    );       

    reset_global: process
    begin
        rst <= '1';
        A_rst <= '1';
        wait for period_time*2;
        rst <= '0';
        A_rst <= '0';
        wait;
    end process;
    
    sim_time_proc: process
    begin
        wait for 10 us;
        finished <= '1';
        wait;
    end process sim_time_proc;

    clk_proc: process
    begin
        while finished /= '1' loop
            clk <= '0';
            wait for period_time/2;
            clk <= '1';
            wait for period_time/2;
        end loop;
        wait;
    end process clk_proc;

    process
    begin
        wait for period_time;
        -- Escreve valor 10 no registrador 1
        A_source   <= "01";
        B_source   <= '0';  
        REG_source <= '1';  
        wr_en      <= '1';
        A_wr_en    <= '1';
        operation  <= "001"; -- sum
        w_address  <= "0001";
        r_address  <= "0001";
        immediate  <= to_unsigned(10, 16);
        wait for period_time;

        wr_en      <= '0';
        A_wr_en    <= '0';
        wait for period_time;

        -- Escreve valor 20 no registrador 4
        REG_source <= '1';
        wr_en      <= '1';
        A_wr_en    <= '0';
        w_address  <= "0100";
        immediate  <= to_unsigned(21, 16);
        wait for period_time;

        wr_en      <= '0';
        wait for period_time;

        -- Carrega valor do registrador 4 no acumulador
        A_source   <= "10"; 
        r_address  <= "0100";
        A_wr_en    <= '1';
        wait for period_time;

        A_wr_en    <= '0';
        wait for period_time;

        -- Subtrai registrador 1 do acumulador
        A_source   <= "00"; 
        B_source   <= '0';  
        r_address  <= "0001";
        operation  <= "010"; -- sub
        A_wr_en    <= '1';
        wait for period_time;

        A_wr_en    <= '0';
        wait for period_time;

        -- Guarda acumulador no registrador 3
        REG_source <= '0'; 
        wr_en      <= '1';
        w_address  <= "0011";
        wait for period_time;

        wr_en      <= '0';
        wait;

    end process;
end architecture;

wave.vcd
$date
  Wed May 21 18:49:20 2025
$end
$version
  GHDL v0
$end
$timescale
  1 fs
$end
$scope module standard $end
$upscope $end
$scope module std_logic_1164 $end
$upscope $end
$scope module numeric_std $end
$upscope $end
$scope module top_level_tb $end
$comment period_time is not handled $end
$var reg 1 ! finished $end
$var reg 1 " clk $end
$var reg 1 # rst $end
$var reg 1 $ wr_en $end
$var reg 1 % b_source $end
$var reg 1 & a_rst $end
$var reg 1 ' a_wr_en $end
$var reg 2 ( a_source[1:0] $end
$var reg 3 ) operation[2:0] $end
$var reg 1 * reg_source $end
$var reg 4 + w_address[3:0] $end
$var reg 4 , r_address[3:0] $end
$var reg 16 - immediate[15:0] $end
$var reg 1 . zero $end
$var reg 1 / negative $end
$var reg 1 0 carry $end
$var reg 1 1 overflow $end
$var reg 16 2 reg[15:0] $end
$var reg 16 3 rega[15:0] $end
$scope module uut $end
$var reg 2 4 a_source[1:0] $end
$var reg 1 5 b_source $end
$var reg 1 6 reg_source $end
$var reg 1 7 clk $end
$var reg 1 8 rst $end
$var reg 1 9 a_rst $end
$var reg 1 : wr_en $end
$var reg 1 ; a_wr_en $end
$var reg 3 < operation[2:0] $end
$var reg 4 = w_address[3:0] $end
$var reg 4 > r_address[3:0] $end
$var reg 16 ? immediate[15:0] $end
$var reg 1 @ zero $end
$var reg 1 A negative $end
$var reg 1 B carry $end
$var reg 1 C overflow $end
$var reg 16 D reg[15:0] $end
$var reg 16 E rega[15:0] $end
$var reg 16 F acum_out[15:0] $end
$var reg 16 G acum_in[15:0] $end
$var reg 16 H banco_out[15:0] $end
$var reg 16 I ula_out[15:0] $end
$var reg 16 J operando_b[15:0] $end
$var reg 16 K reg_in[15:0] $end
$scope module acumulador $end
$var reg 1 L clk $end
$var reg 1 M rst $end
$var reg 1 N wr_en $end
$var reg 16 O data_in[15:0] $end
$var reg 16 P data_out[15:0] $end
$var reg 16 Q registro[15:0] $end
$upscope $end
$scope module banco $end
$var reg 1 R clk $end
$var reg 1 S rst $end
$var reg 1 T wr_en $end
$var reg 4 U w_address[3:0] $end
$var reg 4 V r_address[3:0] $end
$var reg 16 W data_in[15:0] $end
$var reg 16 X data_out[15:0] $end
$var reg 1 Y we0 $end
$var reg 1 Z we1 $end
$var reg 1 [ we2 $end
$var reg 1 \ we3 $end
$var reg 1 ] we4 $end
$var reg 1 ^ we5 $end
$var reg 1 _ we6 $end
$var reg 1 ` we7 $end
$var reg 1 a we8 $end
$var reg 1 b we9 $end
$var reg 16 c registrador_0[15:0] $end
$var reg 16 d registrador_1[15:0] $end
$var reg 16 e registrador_2[15:0] $end
$var reg 16 f registrador_3[15:0] $end
$var reg 16 g registrador_4[15:0] $end
$var reg 16 h registrador_5[15:0] $end
$var reg 16 i registrador_6[15:0] $end
$var reg 16 j registrador_7[15:0] $end
$var reg 16 k registrador_8[15:0] $end
$var reg 16 l registrador_9[15:0] $end
$scope module reg0 $end
$var reg 1 m clk $end
$var reg 1 n rst $end
$var reg 1 o wr_en $end
$var reg 16 p data_in[15:0] $end
$var reg 16 q data_out[15:0] $end
$var reg 16 r registro[15:0] $end
$upscope $end
$scope module reg1 $end
$var reg 1 s clk $end
$var reg 1 t rst $end
$var reg 1 u wr_en $end
$var reg 16 v data_in[15:0] $end
$var reg 16 w data_out[15:0] $end
$var reg 16 x registro[15:0] $end
$upscope $end
$scope module reg2 $end
$var reg 1 y clk $end
$var reg 1 z rst $end
$var reg 1 { wr_en $end
$var reg 16 | data_in[15:0] $end
$var reg 16 } data_out[15:0] $end
$var reg 16 !" registro[15:0] $end
$upscope $end
$scope module reg3 $end
$var reg 1 "" clk $end
$var reg 1 #" rst $end
$var reg 1 $" wr_en $end
$var reg 16 %" data_in[15:0] $end
$var reg 16 &" data_out[15:0] $end
$var reg 16 '" registro[15:0] $end
$upscope $end
$scope module reg4 $end
$var reg 1 (" clk $end
$var reg 1 )" rst $end
$var reg 1 *" wr_en $end
$var reg 16 +" data_in[15:0] $end
$var reg 16 ," data_out[15:0] $end
$var reg 16 -" registro[15:0] $end
$upscope $end
$scope module reg5 $end
$var reg 1 ." clk $end
$var reg 1 /" rst $end
$var reg 1 0" wr_en $end
$var reg 16 1" data_in[15:0] $end
$var reg 16 2" data_out[15:0] $end
$var reg 16 3" registro[15:0] $end
$upscope $end
$scope module reg6 $end
$var reg 1 4" clk $end
$var reg 1 5" rst $end
$var reg 1 6" wr_en $end
$var reg 16 7" data_in[15:0] $end
$var reg 16 8" data_out[15:0] $end
$var reg 16 9" registro[15:0] $end
$upscope $end
$scope module reg7 $end
$var reg 1 :" clk $end
$var reg 1 ;" rst $end
$var reg 1 <" wr_en $end
$var reg 16 =" data_in[15:0] $end
$var reg 16 >" data_out[15:0] $end
$var reg 16 ?" registro[15:0] $end
$upscope $end
$scope module reg8 $end
$var reg 1 @" clk $end
$var reg 1 A" rst $end
$var reg 1 B" wr_en $end
$var reg 16 C" data_in[15:0] $end
$var reg 16 D" data_out[15:0] $end
$var reg 16 E" registro[15:0] $end
$upscope $end
$scope module reg9 $end
$var reg 1 F" clk $end
$var reg 1 G" rst $end
$var reg 1 H" wr_en $end
$var reg 16 I" data_in[15:0] $end
$var reg 16 J" data_out[15:0] $end
$var reg 16 K" registro[15:0] $end
$upscope $end
$upscope $end
$scope module ula $end
$var reg 16 L" input_a[15:0] $end
$var reg 16 M" input_b[15:0] $end
$var reg 16 N" result[15:0] $end
$var reg 3 O" operation[2:0] $end
$var reg 1 P" zero $end
$var reg 1 Q" negative $end
$var reg 1 R" carry $end
$var reg 1 S" overflow $end
$var reg 16 T" calc[15:0] $end
$upscope $end
$upscope $end
$upscope $end
$enddefinitions $end
#0
0!
0"
1#
U$
U%
1&
U'
bUU (
bUUU )
U*
bUUUU +
bUUUU ,
bUUUUUUUUUUUUUUUU -
1.
0/
00
01
b0000000000000000 2
b0000000000000000 3
bUU 4
U5
U6
07
18
19
U:
U;
bUUU <
bUUUU =
bUUUU >
bUUUUUUUUUUUUUUUU ?
1@
0A
0B
0C
b0000000000000000 D
b0000000000000000 E
b0000000000000000 F
b0000000000000000 G
b0000000000000000 H
b0000000000000000 I
bUUUUUUUUUUUUUUUU J
bUUUUUUUUUUUUUUUU K
0L
1M
UN
b0000000000000000 O
b0000000000000000 P
b0000000000000000 Q
0R
1S
UT
bUUUU U
bUUUU V
bUUUUUUUUUUUUUUUU W
b0000000000000000 X
0Y
0Z
0[
0\
0]
0^
0_
0`
0a
0b
b0000000000000000 c
b0000000000000000 d
b0000000000000000 e
b0000000000000000 f
b0000000000000000 g
b0000000000000000 h
b0000000000000000 i
b0000000000000000 j
b0000000000000000 k
b0000000000000000 l
0m
1n
0o
bUUUUUUUUUUUUUUUU p
b0000000000000000 q
b0000000000000000 r
0s
1t
0u
bUUUUUUUUUUUUUUUU v
b0000000000000000 w
b0000000000000000 x
0y
1z
0{
bUUUUUUUUUUUUUUUU |
b0000000000000000 }
b0000000000000000 !"
0""
1#"
0$"
bUUUUUUUUUUUUUUUU %"
b0000000000000000 &"
b0000000000000000 '"
0("
1)"
0*"
bUUUUUUUUUUUUUUUU +"
b0000000000000000 ,"
b0000000000000000 -"
0."
1/"
00"
bUUUUUUUUUUUUUUUU 1"
b0000000000000000 2"
b0000000000000000 3"
04"
15"
06"
bUUUUUUUUUUUUUUUU 7"
b0000000000000000 8"
b0000000000000000 9"
0:"
1;"
0<"
bUUUUUUUUUUUUUUUU ="
b0000000000000000 >"
b0000000000000000 ?"
0@"
1A"
0B"
bUUUUUUUUUUUUUUUU C"
b0000000000000000 D"
b0000000000000000 E"
0F"
1G"
0H"
bUUUUUUUUUUUUUUUU I"
b0000000000000000 J"
b0000000000000000 K"
b0000000000000000 L"
bUUUUUUUUUUUUUUUU M"
b0000000000000000 N"
bUUU O"
1P"
0Q"
0R"
0S"
b0000000000000000 T"
#50000000
1"
17
1L
1R
1m
1s
1y
1""
1("
1."
14"
1:"
1@"
1F"
#100000000
0"
1$
0%
1'
b01 (
b001 )
1*
b0001 +
b0001 ,
b0000000000001010 -
0.
1/
11
b01 4
05
16
07
1:
1;
b001 <
b0001 =
b0001 >
b0000000000001010 ?
0@
1A
1C
b0000000000001010 G
b1111111111111111 I
b0000000000000000 J
b0000000000001010 K
0L
1N
b0000000000001010 O
0R
1T
b0001 U
b0001 V
b0000000000001010 W
1Z
0m
b0000000000001010 p
0s
1u
b0000000000001010 v
0y
b0000000000001010 |
0""
b0000000000001010 %"
0("
b0000000000001010 +"
0."
b0000000000001010 1"
04"
b0000000000001010 7"
0:"
b0000000000001010 ="
0@"
b0000000000001010 C"
0F"
b0000000000001010 I"
b0000000000000000 M"
b1111111111111111 N"
b001 O"
0P"
1Q"
1S"
b1111111111111111 T"
#150000000
1"
17
1L
1R
1m
1s
1y
1""
1("
1."
14"
1:"
1@"
1F"
#200000000
0"
0#
0$
0&
0'
07
08
09
0:
0;
0L
0M
0N
0R
0S
0T
0m
0n
0s
0t
0y
0z
0""
0#"
0("
0)"
0."
0/"
04"
05"
0:"
0;"
0@"
0A"
0F"
0G"
#250000000
1"
b0000000000001010 2
17
b0000000000001010 D
b0000000000001010 H
b0000000000001010 J
1L
1R
b0000000000001010 X
b0000000000001010 d
1m
1s
b0000000000001010 w
b0000000000001010 x
1y
1""
1("
1."
14"
1:"
1@"
1F"
b0000000000001010 M"
#300000000
0"
1$
b0100 +
b0000000000010101 -
07
1:
b0100 =
b0000000000010101 ?
b0000000000010101 G
b0000000000010101 K
0L
b0000000000010101 O
0R
1T
b0100 U
b0000000000010101 W
0Z
1]
0m
b0000000000010101 p
0s
0u
b0000000000010101 v
0y
b0000000000010101 |
0""
b0000000000010101 %"
0("
1*"
b0000000000010101 +"
0."
b0000000000010101 1"
04"
b0000000000010101 7"
0:"
b0000000000010101 ="
0@"
b0000000000010101 C"
0F"
b0000000000010101 I"
#350000000
1"
17
1L
1R
b0000000000010101 g
1m
1s
1y
1""
1("
b0000000000010101 ,"
b0000000000010101 -"
1."
14"
1:"
1@"
1F"
#400000000
0"
0$
07
0:
0L
0R
0T
0m
0s
0y
0""
0("
0."
04"
0:"
0@"
0F"
#450000000
1"
17
1L
1R
1m
1s
1y
1""
1("
1."
14"
1:"
1@"
1F"
#500000000
0"
1'
b10 (
b0100 ,
b0000000000010101 2
b10 4
07
1;
b0100 >
b0000000000010101 D
b0000000000010101 G
b0000000000010101 H
b0000000000010101 J
0L
1N
b0000000000010101 O
0R
b0100 V
b0000000000010101 X
0m
0s
0y
0""
0("
0."
04"
0:"
0@"
0F"
b0000000000010101 M"
#550000000
1"
0/
10
01
b0000000000010101 3
17
0A
1B
0C
b0000000000010101 E
b0000000000010101 F
b0000000000010100 I
1L
b0000000000010101 P
b0000000000010101 Q
1R
1m
1s
1y
1""
1("
1."
14"
1:"
1@"
1F"
b0000000000010101 L"
b0000000000010100 N"
0Q"
1R"
0S"
b0000000000010100 T"
#600000000
0"
0'
07
0;
0L
0N
0R
0m
0s
0y
0""
0("
0."
04"
0:"
0@"
0F"
#650000000
1"
17
1L
1R
1m
1s
1y
1""
1("
1."
14"
1:"
1@"
1F"
#700000000
0"
1'
b00 (
b010 )
b0001 ,
0.
b0000000000001010 2
b00 4
07
1;
b010 <
b0001 >
0@
b0000000000001010 D
b0000000000001011 G
b0000000000001010 H
b0000000000001011 I
b0000000000001010 J
0L
1N
b0000000000001011 O
0R
b0001 V
b0000000000001010 X
0m
0s
0y
0""
0("
0."
04"
0:"
0@"
0F"
b0000000000001010 M"
b0000000000001011 N"
b010 O"
0P"
b0000000000001011 T"
#750000000
1"
10
b0000000000001011 3
17
1B
b0000000000001011 E
b0000000000001011 F
b0000000000000001 G
b0000000000000001 I
1L
b0000000000000001 O
b0000000000001011 P
b0000000000001011 Q
1R
1m
1s
1y
1""
1("
1."
14"
1:"
1@"
1F"
b0000000000001011 L"
b0000000000000001 N"
1R"
b0000000000000001 T"
#800000000
0"
0'
07
0;
0L
0N
0R
0m
0s
0y
0""
0("
0."
04"
0:"
0@"
0F"
#850000000
1"
17
1L
1R
1m
1s
1y
1""
1("
1."
14"
1:"
1@"
1F"
#900000000
0"
1$
0*
b0011 +
06
07
1:
b0011 =
b0000000000001011 K
0L
0R
1T
b0011 U
b0000000000001011 W
1\
0]
0m
b0000000000001011 p
0s
b0000000000001011 v
0y
b0000000000001011 |
0""
1$"
b0000000000001011 %"
0("
0*"
b0000000000001011 +"
0."
b0000000000001011 1"
04"
b0000000000001011 7"
0:"
b0000000000001011 ="
0@"
b0000000000001011 C"
0F"
b0000000000001011 I"
#950000000
1"
17
1L
1R
b0000000000001011 f
1m
1s
1y
1""
b0000000000001011 &"
b0000000000001011 '"
1("
1."
14"
1:"
1@"
1F"
#1000000000
0"
0$
07
0:
0L
0R
0T
0m
0s
0y
0""
0("
0."
04"
0:"
0@"
0F"
