ULA/ULA.vhd
library ieee;
use ieee.std_logic.all;
use ieee.numeric_std.all;

-- João Pedro de Andrade Argenton e Lucas Maciel Ferreira
-- Operações escolhidas: adição, subtração, decremento, 'ou' lógico, 'e' lógico e 'ou' exclusivo

entity ULA is 
port (
    input_A : in unsigned(15 downto 0);
    input_B : in unsigned(15 downto 0);
    result  : out unsigned(15 downto 0);

    operation   : in std_logic_vector(2 downto 0);

    zero    : out std_logic;
    negative: out std_logic;
    carry   : out std_logic;
    overflow: out std_logic
    );
end entity;

architecture behavioral of ULA is
    signal calc: unsigned(15 downto 0);

begin
    calc <= (input_A + input_B) when operation = "000" else                 -- Adicao
                (input_B - "0000000000000001") when operation = "001" else  -- Decremento
                (input_A - input_B) when operation = "010" else             -- Subtracao
                (input_A or input_B) when operation = "100" else            -- Ou lógico
                (input_A and input_B) when operation = "101" else           -- E lógico
                (input_A xor input_B) when operation = "110" else           -- Ou exclusivo
                "0000000000000000";

    result <= calc;
    zero <= '1' when (calc = "0000000000000000") else '0';
    negative <= calc(15);
    carry <= '1' when calc < input_A else '0';
    overflow <= '1' when (input_A(15) and input_B(15) and not calc(15)) 
                or (not input_A(15) and not input_B(15) and calc(15)) else 
                '0';
    
end behavioral;

BancoRegs/reg16bit.vhd
library ieee;
use ieee.std_logic_1164.all;
use ieee.numeric_std.all;

-- João Pedro de Andrade Argenton e Lucas Maciel Ferreira

entity reg16bit is
    port (
        clk     : in std_logic;
        rst     : in std_logic;
        wr_en   : in std_logic;
        data_in : in unsigned(15 downto 0);
        data_out: out unsigned(15 downto 0)
    );
end entity;

architecture behavioral of reg16bit is
    signal registro: unsigned(15 downto 0);
begin
    process(clk, rst, wr_en)
    begin
        if rst='1' then
            registro <= "0000000000000000";
        elsif wr_en='1' then
            if rising_edge(clk) then
                registro <= data_in;
            end if;
        end if;
    end process;
    data_out <= registro;
end architecture;

BancoRegs/banco_regs.vhd
library ieee;
use ieee.std_logic_1164.all;
use ieee.numeric_std.all;

-- João Pedro de Andrade Argenton e Lucas Maciel Ferreira

entity Banco_regs is
    port (
        clk         : in std_logic;
        rst         : in std_logic;
        wr_en       : in std_logic;
        w_address   : in std_logic_vector(3 downto 0);
        r_address   : in std_logic_vector(3 downto 0);
        data_in     : in unsigned(15 downto 0);
        data_out    : out unsigned(15 downto 0)
    );
end entity;

architecture structural of Banco_regs is
    signal we0, we1, we2, we3, we4, we5, we6, we7, we8, we9 : std_logic;
    signal registrador_0: unsigned(15 downto 0);
    signal registrador_1: unsigned(15 downto 0);
    signal registrador_2: unsigned(15 downto 0);
    signal registrador_3: unsigned(15 downto 0);
    signal registrador_4: unsigned(15 downto 0);
    signal registrador_5: unsigned(15 downto 0);
    signal registrador_6: unsigned(15 downto 0);
    signal registrador_7: unsigned(15 downto 0);
    signal registrador_8: unsigned(15 downto 0);
    signal registrador_9: unsigned(15 downto 0);

begin
    process(clk, rst, wr_en)
    begin

        reg0 : entity work.reg16bit
        port map(
            clk => clk,
            rst => rst,
            wr_en => we0,
            data_in => data_in,
            data_out => registrador_0
        );

        reg1 : entity work.reg16bit
        port map(
            clk => clk,
            rst => rst,
            wr_en => we1,
            data_in => data_in,
            data_out => registrador_1
        );

        reg2 : entity work.reg16bit
        port map(
            clk => clk,
            rst => rst,
            wr_en => we2,
            data_in => data_in,
            data_out => registrador_2
        );

        reg3 : entity work.reg16bit
        port map(
            clk => clk,
            rst => rst,
            wr_en => we3,
            data_in => data_in,
            data_out => registrador_3
        );

        reg4 : entity work.reg16bit
        port map(
            clk => clk,
            rst => rst,
            wr_en => we4,
            data_in => data_in,
            data_out => registrador_4
        );

        reg5 : entity work.reg16bit
        port map(
            clk => clk,
            rst => rst,
            wr_en => we5,
            data_in => data_in,
            data_out => registrador_5
        );

        reg6 : entity work.reg16bit
        port map(
            clk => clk,
            rst => rst,
            wr_en => we6,
            data_in => data_in,
            data_out => registrador_6
        );

        reg7 : entity work.reg16bit
        port map(
            clk => clk,
            rst => rst,
            wr_en => we7,
            data_in => data_in,
            data_out => registrador_7
        );

        reg8 : entity work.reg16bit
        port map(
            clk => clk,
            rst => rst,
            wr_en => we8,
            data_in => data_in,
            data_out => registrador_8
        );

        reg9 : entity work.reg16bit
        port map(
            clk => clk,
            rst => rst,
            wr_en => we9,
            data_in => data_in,
            data_out => registrador_9
        );

        we0 <= '1' when w_address = "0000" else '0';
        we1 <= '1' when w_address = "0001" else '0';
        we2 <= '1' when w_address = "0010" else '0';
        we3 <= '1' when w_address = "0011" else '0';
        we4 <= '1' when w_address = "0100" else '0';
        we5 <= '1' when w_address = "0101" else '0';
        we6 <= '1' when w_address = "0110" else '0';
        we7 <= '1' when w_address = "0111" else '0';
        we8 <= '1' when w_address = "1000" else '0';
        we9 <= '1' when w_address = "1001" else '0';

        data_out <= registrador_0 when r_address = "0000" else
                    registrador_1 when r_address = "0001" else
                    registrador_2 when r_address = "0010" else
                    registrador_3 when r_address = "0011" else
                    registrador_4 when r_address = "0100" else
                    registrador_5 when r_address = "0101" else
                    registrador_6 when r_address = "0110" else
                    registrador_7 when r_address = "0111" else
                    registrador_8 when r_address = "1000" else
                    registrador_9 when r_address = "1001" else
                    "0000000000000000";
                    
end architecture;

Top_Level.vhd
library ieee;
use ieee.std_logic_1164.all;
use ieee.numeric_std.all;

-- João Pedro de Andrade Argenton e Lucas Maciel Ferreira

entity Top_Level is
    port(
        A_source    : in std_logic_vector(1 downto 0);
        B_source    : in std_logic;
        REG_source  : in std_logic;
        clk         : in std_logic;
        rst         : in std_logic;
        A_rst       : in std_logic;
        wr_en       : in std_logic;
        A_wr_en     : in std_logic;
        operation   : in std_logic_vector(2 downto 0);
        w_address   : in std_logic_vector(3 downto 0);
        r_address   : in std_logic_vector(3 downto 0);
        immediate   : in unsigned(15 downto 0);
        zero        : out std_logic;
        negative    : out std_logic;
        carry       : out std_logic;
        overflow    : out std_logic;
        reg, regA   : out unsigned(15 downto 0)
    );
end entity;

architecture structural of Top_Level is
signal acum_out, acum_in, banco_out, ULA_out: unsigned(15 downto 0);
signal operando_B, reg_in                   : unsigned(15 downto 0);
signal A_we : std_logic;
begin
    acumulador : entity work.reg16bit
    port map(
        clk => clk,
        rst => A_rst,
        wr_en => A_wr_en,
        data_in => acum_in,
        data_out => acum_out
    );

    banco : entity work.Banco_regs
    port map(
        clk => clk,
        rst => rst,
        wr_en => wr_en,
        w_address => w_address,
        r_address => r_address,
        data_in => reg_in,
        data_out => banco_out
    );

    ULA : entity work.ULA
    port map(
        input_A => acum_out,
        input_B => operando_B,
        result => ULA_out,
        operation => operation,
        zero => zero,
        negative => negative,
        carry => carry,
        overflow => overflow
    );

    acum_in <= ULA_out when A_source = "00" else immediate when A_source = "01" else banco_out;
    operando_B <= banco_out when B_source = '0' else immediate;
    reg_in <= acum_out when REG_source = '0' else immediate;
    reg <= banco_out;
    regA <= acum_out;

end architecture;

Top_Level_tb.vhd
library ieee;
use ieee.std_logic_1164.all;
use ieee.numeric_std.all;

-- João Pedro de Andrade Argenton e Lucas Maciel Ferreira

entity Top_Level_tb is
end entity;

architecture testbech of Top_Level_tb is
    signal period_time                      : time      := 100 ns;
    signal finished                         : std_logic := '0';
    signal clk, rst, wr_en                  : std_logic;
    signal B_source, A_rst, A_wr_en         : std_logic;                
    signal A_source                         : std_logic_vector(1 downto 0);
    signal operation                        : std_logic_vector(2 downto 0);
    signal reg_source                       : std_logic;
    signal w_address,r_address              : std_logic_vector(3 downto 0);
    signal immediate                        : unsigned(15 downto 0);
    signal zero, negative, carry, overflow  : std_logic;
    signal reg, regA                               :  unsigned(15 downto 0);
begin
    uut : entity work.Top_Level
    port map(
        A_source    => A_source,
        B_source    => B_source,
        Reg_source => reg_source,
        clk         => clk,
        rst         => rst,
        A_rst       => A_rst,
        wr_en       => wr_en,
        A_wr_en     => A_wr_en,
        operation   => operation,
        w_address   => w_address,
        r_address   => r_address,
        immediate   => immediate,
        zero        => zero,
        negative    => negative,
        carry       => carry,
        overflow    => overflow,
        reg => reg,
        regA => regA
    );       

    reset_global: process
    begin
        rst <= '1';
        A_rst <= '1';
        wait for period_time*2;
        rst <= '0';
        A_rst <= '0';
        wait;
    end process;
    
    sim_time_proc: process
    begin
        wait for 10 us;
        finished <= '1';
        wait;
    end process sim_time_proc;

    clk_proc: process
    begin
        while finished /= '1' loop
            clk <= '0';
            wait for period_time/2;
            clk <= '1';
            wait for period_time/2;
        end loop;
        wait;
    end process clk_proc;

    process
    begin
        wait for period_time;
            -- Subtrai 10 de 5 
            -- 5 -> reg 0001, 10 -> reg 0010

            -- Escreve 5 no reg 0001
            wr_en <= '1';
            REG_source <= '1';
            immediate <= to_unsigned(5, 16);
            w_address <= "0001";

            wait for period_time;

            -- Escreve 10 no reg 0010
            wr_en <= '1';
            immediate <= to_unsigned(10, 16);
            w_address <= "0010";

            wait for period_time;

            -- Carrega 5 no acumulador
            A_source <= "10";
            r_address <= "0001"; -- reg
            A_wr_en <= '1';

            wait for period_time;
            
            -- Subtrai 10 (reg 0010)
            r_address <= "0010";
            operation <= "001";  
            A_source <= "00";
            A_wr_en <= '1';
 


        wait;
    end process;
end architecture;

wave.vcd
$date
  Wed May 21 15:36:55 2025
$end
$version
  GHDL v0
$end
$timescale
  1 fs
$end
$scope module standard $end
$upscope $end
$scope module std_logic_1164 $end
$upscope $end
$scope module numeric_std $end
$upscope $end
$scope module top_level_tb $end
$comment period_time is not handled $end
$var reg 1 ! finished $end
$var reg 1 " clk $end
$var reg 1 # rst $end
$var reg 1 $ wr_en $end
$var reg 1 % b_source $end
$var reg 1 & a_rst $end
$var reg 1 ' a_wr_en $end
$var reg 2 ( a_source[1:0] $end
$var reg 3 ) operation[2:0] $end
$var reg 1 * reg_source $end
$var reg 4 + w_address[3:0] $end
$var reg 4 , r_address[3:0] $end
$var reg 16 - immediate[15:0] $end
$var reg 1 . zero $end
$var reg 1 / negative $end
$var reg 1 0 carry $end
$var reg 1 1 overflow $end
$var reg 16 2 reg[15:0] $end
$var reg 16 3 rega[15:0] $end
$scope module uut $end
$var reg 2 4 a_source[1:0] $end
$var reg 1 5 b_source $end
$var reg 1 6 reg_source $end
$var reg 1 7 clk $end
$var reg 1 8 rst $end
$var reg 1 9 a_rst $end
$var reg 1 : wr_en $end
$var reg 1 ; a_wr_en $end
$var reg 3 < operation[2:0] $end
$var reg 4 = w_address[3:0] $end
$var reg 4 > r_address[3:0] $end
$var reg 16 ? immediate[15:0] $end
$var reg 1 @ zero $end
$var reg 1 A negative $end
$var reg 1 B carry $end
$var reg 1 C overflow $end
$var reg 16 D reg[15:0] $end
$var reg 16 E rega[15:0] $end
$var reg 16 F acum_out[15:0] $end
$var reg 16 G acum_in[15:0] $end
$var reg 16 H banco_out[15:0] $end
$var reg 16 I ula_out[15:0] $end
$var reg 16 J operando_b[15:0] $end
$var reg 16 K reg_in[15:0] $end
$var reg 1 L a_we $end
$scope module acumulador $end
$var reg 1 M clk $end
$var reg 1 N rst $end
$var reg 1 O wr_en $end
$var reg 16 P data_in[15:0] $end
$var reg 16 Q data_out[15:0] $end
$var reg 16 R registro[15:0] $end
$upscope $end
$scope module banco $end
$var reg 1 S clk $end
$var reg 1 T rst $end
$var reg 1 U wr_en $end
$var reg 4 V w_address[3:0] $end
$var reg 4 W r_address[3:0] $end
$var reg 16 X data_in[15:0] $end
$var reg 16 Y data_out[15:0] $end
$var reg 1 Z we0 $end
$var reg 1 [ we1 $end
$var reg 1 \ we2 $end
$var reg 1 ] we3 $end
$var reg 1 ^ we4 $end
$var reg 1 _ we5 $end
$var reg 1 ` we6 $end
$var reg 1 a we7 $end
$var reg 1 b we8 $end
$var reg 1 c we9 $end
$var reg 16 d registrador_0[15:0] $end
$var reg 16 e registrador_1[15:0] $end
$var reg 16 f registrador_2[15:0] $end
$var reg 16 g registrador_3[15:0] $end
$var reg 16 h registrador_4[15:0] $end
$var reg 16 i registrador_5[15:0] $end
$var reg 16 j registrador_6[15:0] $end
$var reg 16 k registrador_7[15:0] $end
$var reg 16 l registrador_8[15:0] $end
$var reg 16 m registrador_9[15:0] $end
$scope module reg0 $end
$var reg 1 n clk $end
$var reg 1 o rst $end
$var reg 1 p wr_en $end
$var reg 16 q data_in[15:0] $end
$var reg 16 r data_out[15:0] $end
$var reg 16 s registro[15:0] $end
$upscope $end
$scope module reg1 $end
$var reg 1 t clk $end
$var reg 1 u rst $end
$var reg 1 v wr_en $end
$var reg 16 w data_in[15:0] $end
$var reg 16 x data_out[15:0] $end
$var reg 16 y registro[15:0] $end
$upscope $end
$scope module reg2 $end
$var reg 1 z clk $end
$var reg 1 { rst $end
$var reg 1 | wr_en $end
$var reg 16 } data_in[15:0] $end
$var reg 16 !" data_out[15:0] $end
$var reg 16 "" registro[15:0] $end
$upscope $end
$scope module reg3 $end
$var reg 1 #" clk $end
$var reg 1 $" rst $end
$var reg 1 %" wr_en $end
$var reg 16 &" data_in[15:0] $end
$var reg 16 '" data_out[15:0] $end
$var reg 16 (" registro[15:0] $end
$upscope $end
$scope module reg4 $end
$var reg 1 )" clk $end
$var reg 1 *" rst $end
$var reg 1 +" wr_en $end
$var reg 16 ," data_in[15:0] $end
$var reg 16 -" data_out[15:0] $end
$var reg 16 ." registro[15:0] $end
$upscope $end
$scope module reg5 $end
$var reg 1 /" clk $end
$var reg 1 0" rst $end
$var reg 1 1" wr_en $end
$var reg 16 2" data_in[15:0] $end
$var reg 16 3" data_out[15:0] $end
$var reg 16 4" registro[15:0] $end
$upscope $end
$scope module reg6 $end
$var reg 1 5" clk $end
$var reg 1 6" rst $end
$var reg 1 7" wr_en $end
$var reg 16 8" data_in[15:0] $end
$var reg 16 9" data_out[15:0] $end
$var reg 16 :" registro[15:0] $end
$upscope $end
$scope module reg7 $end
$var reg 1 ;" clk $end
$var reg 1 <" rst $end
$var reg 1 =" wr_en $end
$var reg 16 >" data_in[15:0] $end
$var reg 16 ?" data_out[15:0] $end
$var reg 16 @" registro[15:0] $end
$upscope $end
$scope module reg8 $end
$var reg 1 A" clk $end
$var reg 1 B" rst $end
$var reg 1 C" wr_en $end
$var reg 16 D" data_in[15:0] $end
$var reg 16 E" data_out[15:0] $end
$var reg 16 F" registro[15:0] $end
$upscope $end
$scope module reg9 $end
$var reg 1 G" clk $end
$var reg 1 H" rst $end
$var reg 1 I" wr_en $end
$var reg 16 J" data_in[15:0] $end
$var reg 16 K" data_out[15:0] $end
$var reg 16 L" registro[15:0] $end
$upscope $end
$upscope $end
$scope module ula $end
$var reg 16 M" input_a[15:0] $end
$var reg 16 N" input_b[15:0] $end
$var reg 16 O" result[15:0] $end
$var reg 3 P" operation[2:0] $end
$var reg 1 Q" zero $end
$var reg 1 R" negative $end
$var reg 1 S" carry $end
$var reg 1 T" overflow $end
$var reg 16 U" calc[15:0] $end
$upscope $end
$upscope $end
$upscope $end
$enddefinitions $end
#0
0!
0"
1#
U$
U%
1&
U'
bUU (
bUUU )
U*
bUUUU +
bUUUU ,
bUUUUUUUUUUUUUUUU -
1.
0/
00
01
b0000000000000000 2
b0000000000000000 3
bUU 4
U5
U6
07
18
19
U:
U;
bUUU <
bUUUU =
bUUUU >
bUUUUUUUUUUUUUUUU ?
1@
0A
0B
0C
b0000000000000000 D
b0000000000000000 E
b0000000000000000 F
b0000000000000000 G
b0000000000000000 H
b0000000000000000 I
bUUUUUUUUUUUUUUUU J
bUUUUUUUUUUUUUUUU K
UL
0M
1N
UO
b0000000000000000 P
b0000000000000000 Q
b0000000000000000 R
0S
1T
UU
bUUUU V
bUUUU W
bUUUUUUUUUUUUUUUU X
b0000000000000000 Y
0Z
0[
0\
0]
0^
0_
0`
0a
0b
0c
b0000000000000000 d
b0000000000000000 e
b0000000000000000 f
b0000000000000000 g
b0000000000000000 h
b0000000000000000 i
b0000000000000000 j
b0000000000000000 k
b0000000000000000 l
b0000000000000000 m
0n
1o
0p
bUUUUUUUUUUUUUUUU q
b0000000000000000 r
b0000000000000000 s
0t
1u
0v
bUUUUUUUUUUUUUUUU w
b0000000000000000 x
b0000000000000000 y
0z
1{
0|
bUUUUUUUUUUUUUUUU }
b0000000000000000 !"
b0000000000000000 ""
0#"
1$"
0%"
bUUUUUUUUUUUUUUUU &"
b0000000000000000 '"
b0000000000000000 ("
0)"
1*"
0+"
bUUUUUUUUUUUUUUUU ,"
b0000000000000000 -"
b0000000000000000 ."
0/"
10"
01"
bUUUUUUUUUUUUUUUU 2"
b0000000000000000 3"
b0000000000000000 4"
05"
16"
07"
bUUUUUUUUUUUUUUUU 8"
b0000000000000000 9"
b0000000000000000 :"
0;"
1<"
0="
bUUUUUUUUUUUUUUUU >"
b0000000000000000 ?"
b0000000000000000 @"
0A"
1B"
0C"
bUUUUUUUUUUUUUUUU D"
b0000000000000000 E"
b0000000000000000 F"
0G"
1H"
0I"
bUUUUUUUUUUUUUUUU J"
b0000000000000000 K"
b0000000000000000 L"
b0000000000000000 M"
bUUUUUUUUUUUUUUUU N"
b0000000000000000 O"
bUUU P"
1Q"
0R"
0S"
0T"
b0000000000000000 U"
#50000000
1"
17
1M
1S
1n
1t
1z
1#"
1)"
1/"
15"
1;"
1A"
1G"
#100000000
0"
1$
1*
b0001 +
b0000000000000101 -
16
07
1:
b0001 =
b0000000000000101 ?
b0000000000000101 J
b0000000000000101 K
0M
0S
1U
b0001 V
b0000000000000101 X
1[
0n
b0000000000000101 q
0t
1v
b0000000000000101 w
0z
b0000000000000101 }
0#"
b0000000000000101 &"
0)"
b0000000000000101 ,"
0/"
b0000000000000101 2"
05"
b0000000000000101 8"
0;"
b0000000000000101 >"
0A"
b0000000000000101 D"
0G"
b0000000000000101 J"
b0000000000000101 N"
#150000000
1"
17
1M
1S
1n
1t
1z
1#"
1)"
1/"
15"
1;"
1A"
1G"
#200000000
0"
0#
0&
b0010 +
b0000000000001010 -
07
08
09
b0010 =
b0000000000001010 ?
b0000000000001010 J
b0000000000001010 K
0M
0N
0S
0T
b0010 V
b0000000000001010 X
0[
1\
0n
0o
b0000000000001010 q
0t
0u
0v
b0000000000001010 w
0z
0{
1|
b0000000000001010 }
0#"
0$"
b0000000000001010 &"
0)"
0*"
b0000000000001010 ,"
0/"
00"
b0000000000001010 2"
05"
06"
b0000000000001010 8"
0;"
0<"
b0000000000001010 >"
0A"
0B"
b0000000000001010 D"
0G"
0H"
b0000000000001010 J"
b0000000000001010 N"
#250000000
1"
17
1M
1S
b0000000000001010 f
1n
1t
1z
b0000000000001010 !"
b0000000000001010 ""
1#"
1)"
1/"
15"
1;"
1A"
1G"
#300000000
0"
1'
b10 (
b0001 ,
b10 4
07
1;
b0001 >
0M
1O
0S
b0001 W
0n
0t
0z
0#"
0)"
0/"
05"
0;"
0A"
0G"
#350000000
1"
17
1M
1S
1n
1t
1z
1#"
1)"
1/"
15"
1;"
1A"
1G"
#400000000
0"
b00 (
b001 )
b0010 ,
0.
1/
11
b0000000000001010 2
b00 4
07
b001 <
b0010 >
0@
1A
1C
b0000000000001010 D
b1111111111111111 G
b0000000000001010 H
b1111111111111111 I
0M
b1111111111111111 P
0S
b0010 W
b0000000000001010 Y
0n
0t
0z
0#"
0)"
0/"
05"
0;"
0A"
0G"
b1111111111111111 O"
b001 P"
0Q"
1R"
1T"
b1111111111111111 U"
#450000000
1"
10
01
b1111111111111111 3
17
1B
0C
b1111111111111111 E
b1111111111111111 F
b1111111111111110 G
b1111111111111110 I
1M
b1111111111111110 P
b1111111111111111 Q
b1111111111111111 R
1S
1n
1t
1z
1#"
1)"
1/"
15"
1;"
1A"
1G"
b1111111111111111 M"
b1111111111111110 O"
1S"
0T"
b1111111111111110 U"
#500000000
0"
07
0M
0S
0n
0t
0z
0#"
0)"
0/"
05"
0;"
0A"
0G"
#550000000
1"
10
b1111111111111110 3
17
1B
b1111111111111110 E
b1111111111111110 F
b1111111111111101 G
b1111111111111101 I
1M
b1111111111111101 P
b1111111111111110 Q
b1111111111111110 R
1S
1n
1t
1z
1#"
1)"
1/"
15"
1;"
1A"
1G"
b1111111111111110 M"
b1111111111111101 O"
1S"
b1111111111111101 U"
#600000000
0"
07
0M
0S
0n
0t
0z
0#"
0)"
0/"
05"
0;"
0A"
0G"
#650000000
1"
10
b1111111111111101 3
17
1B
b1111111111111101 E
b1111111111111101 F
b1111111111111100 G
b1111111111111100 I
1M
b1111111111111100 P
b1111111111111101 Q
b1111111111111101 R
1S
1n
1t
1z
1#"
1)"
1/"
15"
1;"
1A"
1G"
b1111111111111101 M"
b1111111111111100 O"
1S"
b1111111111111100 U"
#700000000
0"
07
0M
0S
0n
0t
0z
0#"
0)"
0/"
05"
0;"
0A"
0G"
#750000000
1"
10
b1111111111111100 3
17
1B
b1111111111111100 E
b1111111111111100 F
b1111111111111011 G
b1111111111111011 I
1M
b1111111111111011 P
b1111111111111100 Q
b1111111111111100 R
1S
1n
1t
1z
1#"
1)"
1/"
15"
1;"
1A"
1G"
b1111111111111100 M"
b1111111111111011 O"
1S"
b1111111111111011 U"
#800000000
0"
07
0M
0S
0n
0t
0z
0#"
0)"
0/"
05"
0;"
0A"
0G"
#850000000
1"
10
b1111111111111011 3
17
1B
b1111111111111011 E
b1111111111111011 F
b1111111111111010 G
b1111111111111010 I
1M
b1111111111111010 P
b1111111111111011 Q
b1111111111111011 R
1S
1n
1t
1z
1#"
1)"
1/"
15"
1;"
1A"
1G"
b1111111111111011 M"
b1111111111111010 O"
1S"
b1111111111111010 U"
#900000000
0"
07
0M
0S
0n
0t
0z
0#"
0)"
0/"
05"
0;"
0A"
0G"
#950000000
1"
10
b1111111111111010 3
17
1B
b1111111111111010 E
b1111111111111010 F
b1111111111111001 G
b1111111111111001 I
1M
b1111111111111001 P
b1111111111111010 Q
b1111111111111010 R
1S
1n
1t
1z
1#"
1)"
1/"
15"
1;"
1A"
1G"
b1111111111111010 M"
b1111111111111001 O"
1S"
b1111111111111001 U"
#1000000000
0"
07
0M
0S
0n
0t
0z
0#"
0)"
0/"
05"
0;"
0A"
0G"
#1050000000
1"
10
b1111111111111001 3
17
1B
b1111111111111001 E
b1111111111111001 F
b1111111111111000 G
b1111111111111000 I
1M
b1111111111111000 P
b1111111111111001 Q
b1111111111111001 R
1S
1n
1t
1z
1#"
1)"
1/"
15"
1;"
1A"
1G"
b1111111111111001 M"
b1111111111111000 O"
1S"
b1111111111111000 U"
#1100000000
0"
07
0M
0S
0n
0t
0z
0#"
0)"
0/"
05"
0;"
0A"
0G"
#1150000000
1"
10
b1111111111111000 3
17
1B
b1111111111111000 E
b1111111111111000 F
b1111111111110111 G
b1111111111110111 I
1M
b1111111111110111 P
b1111111111111000 Q
b1111111111111000 R
1S
1n
1t
1z
1#"
1)"
1/"
15"
1;"
1A"
1G"
b1111111111111000 M"
b1111111111110111 O"
1S"
b1111111111110111 U"
#1200000000
0"
07
0M
0S
0n
0t
0z
0#"
0)"
0/"
05"
0;"
0A"
0G"
#1250000000
1"
10
b1111111111110111 3
17
1B
b1111111111110111 E
b1111111111110111 F
b1111111111110110 G
b1111111111110110 I
1M
b1111111111110110 P
b1111111111110111 Q
b1111111111110111 R
1S
1n
1t
1z
1#"
1)"
1/"
15"
1;"
1A"
1G"
b1111111111110111 M"
b1111111111110110 O"
1S"
b1111111111110110 U"
#1300000000
0"
07
0M
0S
0n
0t
0z
0#"
0)"
0/"
05"
0;"
0A"
0G"
#1350000000
1"
10
b1111111111110110 3
17
1B
b1111111111110110 E
b1111111111110110 F
b1111111111110101 G
b1111111111110101 I
1M
b1111111111110101 P
b1111111111110110 Q
b1111111111110110 R
1S
1n
1t
1z
1#"
1)"
1/"
15"
1;"
1A"
1G"
b1111111111110110 M"
b1111111111110101 O"
1S"
b1111111111110101 U"
#1400000000
0"
07
0M
0S
0n
0t
0z
0#"
0)"
0/"
05"
0;"
0A"
0G"
#1450000000
1"
10
b1111111111110101 3
17
1B
b1111111111110101 E
b1111111111110101 F
b1111111111110100 G
b1111111111110100 I
1M
b1111111111110100 P
b1111111111110101 Q
b1111111111110101 R
1S
1n
1t
1z
1#"
1)"
1/"
15"
1;"
1A"
1G"
b1111111111110101 M"
b1111111111110100 O"
1S"
b1111111111110100 U"
#1500000000
0"
07
0M
0S
0n
0t
0z
0#"
0)"
0/"
05"
0;"
0A"
0G"
#1550000000
1"
10
b1111111111110100 3
17
1B
b1111111111110100 E
b1111111111110100 F
b1111111111110011 G
b1111111111110011 I
1M
b1111111111110011 P
b1111111111110100 Q
b1111111111110100 R
1S
1n
1t
1z
1#"
1)"
1/"
15"
1;"
1A"
1G"
b1111111111110100 M"
b1111111111110011 O"
1S"
b1111111111110011 U"
#1600000000
0"
07
0M
0S
0n
0t
0z
0#"
0)"
0/"
05"
0;"
0A"
0G"
#1650000000
1"
10
b1111111111110011 3
17
1B
b1111111111110011 E
b1111111111110011 F
b1111111111110010 G
b1111111111110010 I
1M
b1111111111110010 P
b1111111111110011 Q
b1111111111110011 R
1S
1n
1t
1z
1#"
1)"
1/"
15"
1;"
1A"
1G"
b1111111111110011 M"
b1111111111110010 O"
1S"
b1111111111110010 U"
#1700000000
0"
07
0M
0S
0n
0t
0z
0#"
0)"
0/"
05"
0;"
0A"
0G"
#1750000000
1"
10
b1111111111110010 3
17
1B
b1111111111110010 E
b1111111111110010 F
b1111111111110001 G
b1111111111110001 I
1M
b1111111111110001 P
b1111111111110010 Q
b1111111111110010 R
1S
1n
1t
1z
1#"
1)"
1/"
15"
1;"
1A"
1G"
b1111111111110010 M"
b1111111111110001 O"
1S"
b1111111111110001 U"
#1800000000
0"
07
0M
0S
0n
0t
0z
0#"
0)"
0/"
05"
0;"
0A"
0G"
#1850000000
1"
10
b1111111111110001 3
17
1B
b1111111111110001 E
b1111111111110001 F
b1111111111110000 G
b1111111111110000 I
1M
b1111111111110000 P
b1111111111110001 Q
b1111111111110001 R
1S
1n
1t
1z
1#"
1)"
1/"
15"
1;"
1A"
1G"
b1111111111110001 M"
b1111111111110000 O"
1S"
b1111111111110000 U"
#1900000000
0"
07
0M
0S
0n
0t
0z
0#"
0)"
0/"
05"
0;"
0A"
0G"
#1950000000
1"
10
b1111111111110000 3
17
1B
b1111111111110000 E
b1111111111110000 F
b1111111111101111 G
b1111111111101111 I
1M
b1111111111101111 P
b1111111111110000 Q
b1111111111110000 R
1S
1n
1t
1z
1#"
1)"
1/"
15"
1;"
1A"
1G"
b1111111111110000 M"
b1111111111101111 O"
1S"
b1111111111101111 U"
#2000000000
0"
07
0M
0S
0n
0t
0z
0#"
0)"
0/"
05"
0;"
0A"
0G"
#2050000000
1"
10
b1111111111101111 3
17
1B
b1111111111101111 E
b1111111111101111 F
b1111111111101110 G
b1111111111101110 I
1M
b1111111111101110 P
b1111111111101111 Q
b1111111111101111 R
1S
1n
1t
1z
1#"
1)"
1/"
15"
1;"
1A"
1G"
b1111111111101111 M"
b1111111111101110 O"
1S"
b1111111111101110 U"
#2100000000
0"
07
0M
0S
0n
0t
0z
0#"
0)"
0/"
05"
0;"
0A"
0G"
#2150000000
1"
10
b1111111111101110 3
17
1B
b1111111111101110 E
b1111111111101110 F
b1111111111101101 G
b1111111111101101 I
1M
b1111111111101101 P
b1111111111101110 Q
b1111111111101110 R
1S
1n
1t
1z
1#"
1)"
1/"
15"
1;"
1A"
1G"
b1111111111101110 M"
b1111111111101101 O"
1S"
b1111111111101101 U"
#2200000000
0"
07
0M
0S
0n
0t
0z
0#"
0)"
0/"
05"
0;"
0A"
0G"
#2250000000
1"
10
b1111111111101101 3
17
1B
b1111111111101101 E
b1111111111101101 F
b1111111111101100 G
b1111111111101100 I
1M
b1111111111101100 P
b1111111111101101 Q
b1111111111101101 R
1S
1n
1t
1z
1#"
1)"
1/"
15"
1;"
1A"
1G"
b1111111111101101 M"
b1111111111101100 O"
1S"
b1111111111101100 U"
#2300000000
0"
07
0M
0S
0n
0t
0z
0#"
0)"
0/"
05"
0;"
0A"
0G"
#2350000000
1"
10
b1111111111101100 3
17
1B
b1111111111101100 E
b1111111111101100 F
b1111111111101011 G
b1111111111101011 I
1M
b1111111111101011 P
b1111111111101100 Q
b1111111111101100 R
1S
1n
1t
1z
1#"
1)"
1/"
15"
1;"
1A"
1G"
b1111111111101100 M"
b1111111111101011 O"
1S"
b1111111111101011 U"
#2400000000
0"
07
0M
0S
0n
0t
0z
0#"
0)"
0/"
05"
0;"
0A"
0G"
#2450000000
1"
10
b1111111111101011 3
17
1B
b1111111111101011 E
b1111111111101011 F
b1111111111101010 G
b1111111111101010 I
1M
b1111111111101010 P
b1111111111101011 Q
b1111111111101011 R
1S
1n
1t
1z
1#"
1)"
1/"
15"
1;"
1A"
1G"
b1111111111101011 M"
b1111111111101010 O"
1S"
b1111111111101010 U"
#2500000000
0"
07
0M
0S
0n
0t
0z
0#"
0)"
0/"
05"
0;"
0A"
0G"
#2550000000
1"
10
b1111111111101010 3
17
1B
b1111111111101010 E
b1111111111101010 F
b1111111111101001 G
b1111111111101001 I
1M
b1111111111101001 P
b1111111111101010 Q
b1111111111101010 R
1S
1n
1t
1z
1#"
1)"
1/"
15"
1;"
1A"
1G"
b1111111111101010 M"
b1111111111101001 O"
1S"
b1111111111101001 U"
#2600000000
0"
07
0M
0S
0n
0t
0z
0#"
0)"
0/"
05"
0;"
0A"
0G"
#2650000000
1"
10
b1111111111101001 3
17
1B
b1111111111101001 E
b1111111111101001 F
b1111111111101000 G
b1111111111101000 I
1M
b1111111111101000 P
b1111111111101001 Q
b1111111111101001 R
1S
1n
1t
1z
1#"
1)"
1/"
15"
1;"
1A"
1G"
b1111111111101001 M"
b1111111111101000 O"
1S"
b1111111111101000 U"
#2700000000
0"
07
0M
0S
0n
0t
0z
0#"
0)"
0/"
05"
0;"
0A"
0G"
